LICENSE.txt
README.md
setup.cfg
setup.py
DeltekLib/DeltekDB.py
DeltekLib/Encryption.py
DeltekLib/FileIO.py
DeltekLib/WebUI.py
DeltekLib/WinRM.py
DeltekLib/__init__.py
DeltekLib/version.py
DeltekLib.egg-info/PKG-INFO
DeltekLib.egg-info/SOURCES.txt
DeltekLib.egg-info/dependency_links.txt
DeltekLib.egg-info/top_level.txt