Metadata-Version: 2.1
Name: DeltekLib
Version: 1.0.5
Summary: Deltek Library
Home-page: https://deltek.com/testautomation
Author: Deltek Systems (Philippines), Ltd.
Author-email: testautomation@deltek.com
License: Copyright
Platform: UNKNOWN
Classifier: Development Status :: 5 - Production/Stable
Classifier: Intended Audience :: Developers
Classifier: Programming Language :: Python
Classifier: License :: Free for non-commercial use
License-File: LICENSE.txt
